puzzle15/puzzle.py
puzzle15-1.0.2.dist-info/licenses/LICENSE
puzzle15-1.0.2.dist-info/METADATA
puzzle15-1.0.2.dist-info/WHEEL
puzzle15-1.0.2.dist-info/top_level.txt
puzzle15-1.0.2.dist-info/RECORD
