Metadata-Version: 2.4
Name: puzzle15
Version: 1.0.2
Summary: Lib to make NxM - 1 sliding puzzles
Author-email: Evaldas Visockas <developersediary@gmail.com>
License: GPL-3.0-or-later
Project-URL: Repository, https://github.com/EvalVis/Puzzle15
Requires-Python: >=3.12
License-File: LICENSE
Dynamic: license-file
